{
    "title": "My Happy Marriage Season 2",
    "poster": "https://img.flawlessfiles.com/_r/300x400/100/c2/a2/c2a246a281ee33d66635458797ce76cf/c2a246a281ee33d66635458797ce76cf.jpg",
    "background": "https://img.flawlessfiles.com/_r/300x400/100/c2/a2/c2a246a281ee33d66635458797ce76cf/c2a246a281ee33d66635458797ce76cf.jpg",
    "description": "The second season of",
    "film_stats": {
        "rating": "PG-13",
        "quality": "HD",
        "subtitles": "10",
        "dubbing": "10",
        "type": "TV",
        "runtime": "24m"
    },
    "japanese_title": "わたしの幸せな結婚",
    "synonyms": [
        "My Blissful Marriage"
    ],
    "aired": "Jan 6, 2025 to ?",
    "premiered": "Winter 2025",
    "duration": "24m",
    "status": "Currently Airing",
    "score": "?",
    "studios": [
        "Kinema Citrus"
    ],
    "producers": [
        "Kadokawa",
        "Glovision",
        "Miracle Bus"
    ],
    "genres": [
        "Drama",
        "Fantasy",
        "Historical",
        "Romance"
    ],
    "characters": [],
    "trailers": [],
    "more_seasons": [
        {
            "title": "Season 1",
            "url": "/my-happy-marriage-18490",
            "poster": "https://img.flawlessfiles.com/_r/100x200/100/c9/81/c9812cf44deea42d936ac74118f3e420/c9812cf44deea42d936ac74118f3e420.jpg"
        },
        {
            "title": "OVA",
            "url": "/my-happy-marriage-18892",
            "poster": "https://img.flawlessfiles.com/_r/100x200/100/ce/55/ce5562e78f5267a9d515f7ac2d692aeb/ce5562e78f5267a9d515f7ac2d692aeb.jpg"
        },
        {
            "title": "Season 2",
            "url": "/my-happy-marriage-season-2-19432",
            "poster": "https://img.flawlessfiles.com/_r/100x200/100/c2/a2/c2a246a281ee33d66635458797ce76cf/c2a246a281ee33d66635458797ce76cf.jpg"
        }
    ],
    "related_anime": [],
    "most_popular_anime": [],
    "recommended_anime": [
        {
            "title": "One Piece: Romance Dawn Story",
            "url": "/one-piece-romance-dawn-story-1860",
            "poster": "https://img.flawlessfiles.com/_r/300x400/100/a7/d7/a7d7242012fbb0209ec15aba2e8edd67/a7d7242012fbb0209ec15aba2e8edd67.jpg",
            "rate": "",
            "subtitles": "1",
            "dubbing": "",
            "episodes": "",
            "type": "OVA",
            "runtime": "33m"
        },
        {
            "title": "Re: Hamatora: Season 2",
            "url": "/re-hamatora-season-2-1862",
            "poster": "https://img.flawlessfiles.com/_r/300x400/100/36/8b/368b56aba83e83b466c194debdf1facd/368b56aba83e83b466c194debdf1facd.jpg",
            "rate": "18+",
            "subtitles": "",
            "dubbing": "",
            "episodes": "",
            "type": "TV",
            "runtime": "24m"
        },
        {
            "title": "Sengoku Basara: Samurai Kings",
            "url": "/sengoku-basara-samurai-kings-1864",
            "poster": "https://img.flawlessfiles.com/_r/300x400/100/7d/98/7d9890e722761a7bd687cbcaf2117183/7d9890e722761a7bd687cbcaf2117183.jpg",
            "rate": "",
            "subtitles": "12",
            "dubbing": "",
            "episodes": "12",
            "type": "TV",
            "runtime": "23m"
        },
        {
            "title": "Soukyuu no Fafner: Right of Left - Single Program",
            "url": "/soukyuu-no-fafner-right-of-left-single-program-1865",
            "poster": "https://img.flawlessfiles.com/_r/300x400/100/75/3e/753e80db1085620684b8e266bb9a439f/753e80db1085620684b8e266bb9a439f.jpg",
            "rate": "",
            "subtitles": "1",
            "dubbing": "",
            "episodes": "",
            "type": "Special",
            "runtime": "51m"
        },
        {
            "title": "Tamayura: Hitotose - Attakai Kaze no Omoide, Nanode",
            "url": "/tamayura-hitotose-attakai-kaze-no-omoide-nanode-1867",
            "poster": "https://img.flawlessfiles.com/_r/300x400/100/55/ca/55ca7c547d9f8302f9ae88ed2883fea7/55ca7c547d9f8302f9ae88ed2883fea7.jpg",
            "rate": "",
            "subtitles": "1",
            "dubbing": "",
            "episodes": "",
            "type": "Special",
            "runtime": "24m"
        },
        {
            "title": "Tokyo Ghoul: \"Jack\"",
            "url": "/tokyo-ghoul-jack-1869",
            "poster": "https://img.flawlessfiles.com/_r/300x400/100/54/20/5420cc09fa1fcc9ac76f21c306d48967/5420cc09fa1fcc9ac76f21c306d48967.jpg",
            "rate": "18+",
            "subtitles": "",
            "dubbing": "",
            "episodes": "",
            "type": "OVA",
            "runtime": "30m"
        },
        {
            "title": "Someone's Gaze",
            "url": "/someones-gaze-1878",
            "poster": "https://img.flawlessfiles.com/_r/300x400/100/71/ff/71ff5466993c143c0a146f959e1b7e6d/71ff5466993c143c0a146f959e1b7e6d.jpg",
            "rate": "",
            "subtitles": "1",
            "dubbing": "",
            "episodes": "",
            "type": "Movie",
            "runtime": "6m"
        },
        {
            "title": "Fuyu no Sonata",
            "url": "/fuyu-no-sonata-1880",
            "poster": "https://img.flawlessfiles.com/_r/300x400/100/cc/13/cc133eac6f42444bcd3218f02ab2ebb0/cc133eac6f42444bcd3218f02ab2ebb0.jpg",
            "rate": "",
            "subtitles": "26",
            "dubbing": "",
            "episodes": "26",
            "type": "TV",
            "runtime": "25m"
        },
        {
            "title": "[RAW] Grimm's Fairy Tale Classics",
            "url": "/grimms-fairy-tale-classics-1881",
            "poster": "https://img.flawlessfiles.com/_r/300x400/100/43/80/43806da63e265af8e818e12f81767400/43806da63e265af8e818e12f81767400.jpg",
            "rate": "",
            "subtitles": "24",
            "dubbing": "",
            "episodes": "24",
            "type": "TV",
            "runtime": "24m"
        },
        {
            "title": "I Can't Understand What My Husband Is Saying: 2nd Thread",
            "url": "/i-cant-understand-what-my-husband-is-saying-2nd-thread-1877",
            "poster": "https://img.flawlessfiles.com/_r/300x400/100/41/37/413787832fc1cf21fd1c017115580870/413787832fc1cf21fd1c017115580870.jpg",
            "rate": "",
            "subtitles": "13",
            "dubbing": "",
            "episodes": "13",
            "type": "TV",
            "runtime": "3m"
        },
        {
            "title": "Oblivion Island: Haruka and the Magic Mirror",
            "url": "/oblivion-island-haruka-and-the-magic-mirror-1886",
            "poster": "https://img.flawlessfiles.com/_r/300x400/100/36/ac/36acd23196377d0b4ce9b7020722a1e9/36acd23196377d0b4ce9b7020722a1e9.jpg",
            "rate": "",
            "subtitles": "1",
            "dubbing": "1",
            "episodes": "",
            "type": "Movie",
            "runtime": "98m"
        },
        {
            "title": "A Sister's All You Need",
            "url": "/a-sisters-all-you-need-1887",
            "poster": "https://img.flawlessfiles.com/_r/300x400/100/2f/42/2f4285e61df1b6efae0c9c7382b2d1bc/2f4285e61df1b6efae0c9c7382b2d1bc.jpg",
            "rate": "18+",
            "subtitles": "",
            "dubbing": "",
            "episodes": "",
            "type": "TV",
            "runtime": "23m"
        },
        {
            "title": "Jewelpet Twinkle☆",
            "url": "/jewelpet-twinkle-1888",
            "poster": "https://img.flawlessfiles.com/_r/300x400/100/7d/7a/7d7a972a16701c1a7620075946739864/7d7a972a16701c1a7620075946739864.jpg",
            "rate": "",
            "subtitles": "52",
            "dubbing": "",
            "episodes": "52",
            "type": "TV",
            "runtime": "24m"
        },
        {
            "title": "Kaikan Phrase",
            "url": "/kaikan-phrase-1889",
            "poster": "https://img.flawlessfiles.com/_r/300x400/100/6f/cb/6fcb87276dae6f7b83e4c7591a2e4c47/6fcb87276dae6f7b83e4c7591a2e4c47.jpg",
            "rate": "",
            "subtitles": "44",
            "dubbing": "",
            "episodes": "44",
            "type": "TV",
            "runtime": "24m"
        },
        {
            "title": "Kamichu!",
            "url": "/kamichu-1890",
            "poster": "https://img.flawlessfiles.com/_r/300x400/100/64/de/64de30d582389b759e37efbb32b77344/64de30d582389b759e37efbb32b77344.jpg",
            "rate": "",
            "subtitles": "12",
            "dubbing": "12",
            "episodes": "12",
            "type": "TV",
            "runtime": "26m"
        },
        {
            "title": "The Beast Claw",
            "url": "/the-beast-claw-1892",
            "poster": "https://img.flawlessfiles.com/_r/300x400/100/86/48/8648f94b450ce3e65db62c6a8704509e/8648f94b450ce3e65db62c6a8704509e.jpg",
            "rate": "18+",
            "subtitles": "",
            "dubbing": "",
            "episodes": "",
            "type": "TV",
            "runtime": "23m"
        },
        {
            "title": "Record of Lodoss War",
            "url": "/record-of-lodoss-war-1893",
            "poster": "https://img.flawlessfiles.com/_r/300x400/100/7a/18/7a18c637c62768846d68f6705ee1924f/7a18c637c62768846d68f6705ee1924f.jpg",
            "rate": "18+",
            "subtitles": "",
            "dubbing": "",
            "episodes": "",
            "type": "OVA",
            "runtime": "25m"
        },
        {
            "title": "Ahiru no Sora",
            "url": "/ahiru-no-sora-1896",
            "poster": "https://img.flawlessfiles.com/_r/300x400/100/59/af/59aff6067ed5a4b28eca247abc02bfa8/59aff6067ed5a4b28eca247abc02bfa8.jpg",
            "rate": "",
            "subtitles": "50",
            "dubbing": "50",
            "episodes": "50",
            "type": "TV",
            "runtime": "24m"
        }
    ]
}